torloc/__init__.py
torloc/tor_darwin.zip
torloc/tor_linux.zip
torloc/tor_win32.zip
torloc/torloc.py
torloc-1.0.0.data/data/LICENSE
torloc-1.0.0.data/data/README.md
torloc-1.0.0.dist-info/LICENSE
torloc-1.0.0.dist-info/METADATA
torloc-1.0.0.dist-info/WHEEL
torloc-1.0.0.dist-info/top_level.txt
torloc-1.0.0.dist-info/RECORD
