Metadata-Version: 2.1
Name: torloc
Version: 1.0.0
Summary: A Python tool for running multiple Tor services on local ports
Home-page: https://github.com/mrgyber/torloc
Author: Nikita Kudryavtsev
Author-email: mrgyber@mail.ru
License: MIT
Keywords: tor,proxy
Platform: UNKNOWN
Requires-Python: >=3.4
Requires-Dist: PySocks
